{"ide_main_scene":{"__class":"DisplayLayout","height_type":4,"width_type":4,"__childs":[{"__class":"Grid3","height_type":4,"height_value":0,"description":"主界面","show_up":{"__class":"DisplayLayout","__childs":[{"green":0.23529411764706,"height_type":4,"width_type":4,"blue":0.23921568627451,"red":0.23529411764706,"__class":"Quad"},{"type":1,"height_type":4,"__link":"_main_menu","__target_class":["ALittleIDE","IDEUIMainMenu"],"y_type":3,"__childs":[{"__extends":"usual_menu_button","__event":[{"func":"HandleFileMenuClick","type":"ALittle.UIClickEvent"}],"text":"项目","__module":"AUIPlugin"},{"__extends":"usual_menu_button","__event":[{"func":"HandleEditMenuClick","type":"ALittle.UIClickEvent"}],"text":"编辑","__module":"AUIPlugin"},{"__extends":"usual_menu_button","__event":[{"func":"HandleRunMenuClick","type":"ALittle.UIClickEvent"}],"text":"运行","__module":"AUIPlugin"},{"__extends":"usual_menu_button","__event":[{"func":"HandleToolMenuClick","type":"ALittle.UIClickEvent"}],"text":"工具","__module":"AUIPlugin"},{"__extends":"usual_menu_button","__event":[{"func":"HandleHelpMenuClick","type":"ALittle.UIClickEvent"}],"text":"帮助","__module":"AUIPlugin"}],"x_value":38,"gap":1,"__class":"Linear"},{"__target_class":["ALittleIDE","IDEUIAccount"],"height_type":4,"__link":"_account","x_type":4,"width_value":141,"__childs":[{"x_value":4,"__link":"_account_dropdown","__extends":"dropdown","data_list":["登录"],"y_type":3,"x_type":4,"visible":false,"width_value":97,"__event":[{"func":"HandleAccountDropdownChange","type":"ALittle.UISelectChangedEvent"}],"__module":"AUIPlugin"},{"__class":"Image","x_value":53,"y_type":3,"height_value":17,"__link":"_account_icon","width_value":17,"x_type":4,"texture_name":"head_icon.png"},{"__class":"Text","x_value":6,"underline":true,"font_path":"Miui-Regular.ttf","__event":[{"func":"HandleAccountLoginLB","type":"ALittle.UILButtonDownEvent"}],"y_type":3,"font_size":13,"hand_cursor":true,"x_type":4,"text":"请登录","__link":"_account_login"}],"__class":"DisplayLayout"},{"__target_class":["ALittleIDE","IDEUIProjectDropdown"],"height_type":4,"width_type":4,"x_type":3,"__childs":[{"y_type":3,"__link":"_current_project_name","text":"当前没有打开的项目","x_type":3,"__event":[{"func":"HandlePeojectSelectChange","type":"ALittle.UISelectChangedEvent"}],"width_value":201,"__extends":"dropdown","__module":"AUIPlugin"}],"width_value":987,"__link":"_project_dropdown","__class":"DisplayLayout"},{"texture_name":"small_icon.png","x_value":2,"y_type":3,"height_value":30,"width_value":30,"__class":"Image"}]},"width_type":4,"up_size":33,"width_value":0,"show_center":{"__target_class":["ALittleIDE","IDEUICenter"],"height_type":4,"width_type":4,"__childs":[{"__class":"Grid3","height_type":4,"width_type":4,"up_size":35,"__link":"_ui_edit_container","type":2,"show_center":{"__class":"Grid3","__link":"_right_edit_grid3","up_size":440,"show_up":{"__class":"DisplayLayout","height_type":4,"width_type":4,"__childs":[{"green":0.14509803921569,"height_type":4,"width_type":4,"blue":0.14901960784314,"red":0.14509803921569,"__class":"Quad"},{"__class":"Quad","alpha":0,"x_type":4,"__event":[{"type":"ALittle.UIMoveInEvent","func":"System_SetHDragCursor","logic":["ALittle"]},{"func":"HandleLeftEditResizeDrag","type":"ALittle.UIButtonDragEvent"},{"type":"ALittle.UIMoveOutEvent","func":"System_SetNormalCursor","logic":["ALittle"]}],"width_value":3,"height_type":4,"height_value":0},{"type":2,"height_type":4,"__link":"_control_edit_grid3","height_value":0,"width_type":4,"up_size":350,"show_up":{"__class":"DisplayLayout","__childs":[{"green":0.14509803921569,"x_value":1,"width_type":4,"height_value":25,"blue":0.14901960784314,"red":0.14509803921569,"__class":"Quad"},{"__childs":[{"description":"控件树","__link":"_control_tree","__extends":"ide_control_detail_layout","__target_class":["ALittleIDE","IDEUIControlTree"],"__module":"ALittleIDE"},{"description":"笔刷","__link":"_tile_brush_edit","__extends":"ide_brush_detail_layout","__module":"ALittleIDE"}],"height_type":4,"width_type":4,"__link":"_detail_tree_tab","__extends":"tab","width_value":0,"y_type":4,"__module":"AUIPlugin"}]},"width_value":3,"show_center":{"__class":"DisplayLayout","__childs":[{"__class":"Quad","alpha":0,"width_type":4,"height_value":3,"__event":[{"type":"ALittle.UIMoveInEvent","func":"System_SetVDragCursor","logic":["ALittle"]},{"func":"HandleControlEditResizeDrag","type":"ALittle.UIButtonDragEvent"},{"type":"ALittle.UIMoveOutEvent","func":"System_SetNormalCursor","logic":["ALittle"]}],"width_value":0},{"green":0.14509803921569,"x_value":1,"red":0.14509803921569,"height_value":25,"y_value":3,"blue":0.14901960784314,"width_type":4,"__class":"Quad"},{"height_type":4,"__link":"_project_edit_tab","height_value":3,"__extends":"tab","width_type":4,"__childs":[{"__class":"DisplayLayout","__childs":[{"__class":"Grid3","height_value":23,"down_size":52,"show_down":{"__extends":"usual_button","__event":[{"func":"HandleControlSearchClick","type":"ALittle.UIClickEvent"}],"text":"搜索","__module":"AUIPlugin"},"show_center":{"type":1,"height_type":4,"width_type":4,"show_center":{"__event":[{"func":"HandleControlSearchClick","type":"ALittle.UIEnterKeyEvent"},{"func":"HandleControlSearchClick","type":"ALittle.UIChangedEvent"}],"__extends":"image_input","__link":"_control_search_key","__module":"AUIPlugin"},"gap":1,"__class":"Grid3"},"width_type":4,"x_type":3,"y_value":5,"width_value":10,"gap":2,"type":1},{"y_value":5,"height_type":4,"__link":"_control_scroll_screen","height_value":38,"__extends":"scroll_screen","y_type":4,"x_type":3,"width_value":10,"width_type":4,"__module":"AUIPlugin"}],"__link":"_control_list","height_value":400,"width_value":400,"description":"控件库","__target_class":["ALittleIDE","IDEUIControlList"]},{"__class":"DisplayLayout","__childs":[{"__class":"Grid3","height_value":23,"down_size":52,"show_down":{"__extends":"usual_button","__event":[{"func":"HandleCodeSearchClick","type":"ALittle.UIClickEvent"}],"text":"搜索","__module":"AUIPlugin"},"show_center":{"type":1,"height_type":4,"width_type":4,"show_center":{"__event":[{"func":"HandleCodeSearchClick","type":"ALittle.UIEnterKeyEvent"},{"func":"HandleCodeSearchClick","type":"ALittle.UIChangedEvent"}],"__extends":"image_input","__link":"_code_search_key","__module":"AUIPlugin"},"gap":1,"__class":"Grid3"},"width_type":4,"x_type":3,"y_value":5,"width_value":10,"gap":2,"type":1},{"__class":"ScrollScreen","height_type":4,"__link":"_code_scroll_screen","height_value":38,"__extends":"scroll_screen","y_type":4,"x_type":3,"width_type":4,"width_value":10,"y_value":5,"__module":"AUIPlugin"}],"__link":"_code_list","height_value":400,"width_value":400,"description":"代码库","__target_class":["ALittleIDE","IDEUICodeList"]},{"__class":"DisplayLayout","height_type":4,"width_type":4,"__childs":[{"__link":"_tile_list","height_value":10,"__extends":"file_tree_layout","__target_class":["ALittleIDE","IDEUITileList"],"y_type":3,"x_type":3,"width_value":10,"__module":"AUIPlugin"}],"description":"地图库"},{"description":"地块库","__link":"_tile_brush_list","__extends":"ide_tile_detail_layout","__target_class":["ALittleIDE","IDEUITileBrushList"],"__module":"ALittleIDE"},{"__class":"DisplayLayout","__childs":[{"__class":"Grid3","height_value":23,"down_size":52,"show_down":{"__extends":"usual_button","__event":[{"func":"HandleProjectSearchClick","type":"ALittle.UIClickEvent"}],"text":"搜索","__module":"AUIPlugin"},"show_center":{"__event":[{"func":"HandleProjectSearchClick","type":"ALittle.UIEnterKeyEvent"}],"__extends":"image_input","__link":"_project_search_key","__module":"AUIPlugin"},"width_type":4,"x_type":3,"y_value":5,"width_value":10,"gap":2,"type":1},{"y_value":5,"height_type":4,"__link":"_project_scroll_screen","height_value":38,"__extends":"scroll_screen","y_type":4,"x_type":3,"width_type":4,"width_value":10,"container":{"__extends":"scroll_screen_linear","__module":"AUIPlugin"},"__module":"AUIPlugin"}],"__link":"_project_list","height_value":400,"width_value":400,"description":"项目库","__target_class":["ALittleIDE","IDEUIProjectList"]}],"width_value":0,"y_type":4,"__module":"AUIPlugin"}]},"__class":"Grid3"}]},"show_center":{"__class":"DisplayLayout","__childs":[{"__class":"Grid3","height_type":4,"width_type":4,"show_down":{"__class":"DisplayLayout","height_type":4,"width_type":4,"__childs":[{"green":0.11764705882353,"height_type":4,"width_type":4,"blue":0.11764705882353,"red":0.11764705882353,"__class":"Quad"},{"green":0.14509803921569,"width_type":4,"height_value":25,"blue":0.14901960784314,"red":0.14509803921569,"__class":"Quad"},{"__class":"Quad","alpha":0,"width_type":4,"height_value":3,"__event":[{"type":"ALittle.UIMoveInEvent","func":"System_SetVDragCursor","logic":["ALittle"]},{"func":"HandleQuickEditResizeDrag","type":"ALittle.UIButtonDragEvent"},{"type":"ALittle.UIMoveOutEvent","func":"System_SetNormalCursor","logic":["ALittle"]}],"width_value":0},{"__childs":[{"__class":"DisplayLayout","height_type":4,"width_type":4,"__link":"_control_anti","description":"动画编辑器","__target_class":["ALittleIDE","IDEUIControlAnti"]}],"height_type":4,"width_type":4,"__link":"_project_quick_tab","__extends":"tab","width_value":0,"y_type":4,"__module":"AUIPlugin"},{"__class":"TextCheckButton","x_value":3,"show_selected_disabled":{"__class":"Image","texture_name":"fold_down.png"},"show_selected_over":{"__class":"Image","texture_name":"fold_down.png"},"width_value":18,"selected":true,"show_disabled":{"__class":"Image","texture_name":"fold_up.png"},"__link":"_quick_fold_updown","height_value":15,"__event":[{"func":"HandleQuickFoldChanged","type":"ALittle.UIChangedEvent"}],"show_selected_down":{"__class":"Image","texture_name":"fold_down.png"},"show_selected_up":{"__class":"Image","texture_name":"fold_down.png"},"show_up":{"__class":"Image","texture_name":"fold_up.png"},"show_down":{"__class":"Image","texture_name":"fold_up.png"},"show_over":{"__class":"Image","texture_name":"fold_up.png"},"x_type":4,"y_value":6.5}]},"show_center":{"__target_class":["ALittleIDE","IDEContentEdit"],"height_type":4,"width_type":4,"__childs":[{"green":0.11764705882353,"height_type":4,"width_type":4,"__link":"_main_tab_bg","blue":0.11764705882353,"red":0.11764705882353,"__class":"Quad"},{"green":0.14509803921569,"width_type":4,"height_value":25,"blue":0.14901960784314,"red":0.14509803921569,"__class":"Quad"},{"height_type":4,"__link":"_main_tab","height_value":0,"__extends":"tab","width_type":4,"view_margin":20,"width_value":0,"__module":"AUIPlugin"},{"y_value":6,"x_value":3,"x_type":4,"__extends":"ide_tab_right_button","__event":[{"func":"HandleTabRightExMenu","type":"ALittle.UIClickEvent"}]}],"__link":"_content_edit","__class":"DisplayLayout"},"down_size":250,"__link":"_quick_edit_grid3"}]},"type":1},"show_up":{"__class":"DisplayLayout","__childs":[{"green":0.2,"height_type":4,"width_type":4,"blue":0.2,"red":0.2,"__class":"Quad"},{"__class":"DisplayLayout","height_type":4,"width_type":4,"__childs":[{"x_value":8,"__link":"_tool_singleselect","height_value":25,"__extends":"usual_status_button","group_name":"idetoolbutton201602011338","y_type":3,"__event":[{"func":"HandleToolSingleSelect","type":"ALittle.UIChangedEvent"}],"width_value":30,"selected":true,"__module":"AUIPlugin"},{"__class":"Image","x_value":15,"y_type":3,"height_value":14,"disabled":true,"width_value":17,"texture_name":"tool_move.png"},{"x_value":38,"__link":"_tool_handdrag","height_value":25,"__extends":"usual_status_button","group_name":"idetoolbutton201602011338","y_type":3,"width_value":30,"__event":[{"func":"HandleToolHandDrag","type":"ALittle.UIChangedEvent"}],"__module":"AUIPlugin"},{"__class":"Image","x_value":44,"y_type":3,"height_value":17,"disabled":true,"width_value":17,"texture_name":"tool_hold.png"},{"x_value":69,"__link":"_tool_presee","height_value":25,"__extends":"usual_status_button","group_name":"idetoolbutton201602011338","y_type":3,"width_value":30,"__event":[{"func":"HandleToolPreSee","type":"ALittle.UIChangedEvent"}],"__module":"AUIPlugin"},{"__class":"Image","x_value":77,"y_type":3,"height_value":10,"disabled":true,"width_value":12,"texture_name":"tool_presee.png"},{"__link":"_tool_h_align_left","x_value":143,"y_type":3,"height_value":25,"__extends":"tool_button","width_value":25,"__event":[{"func":"HandleToolHLAlign","type":"ALittle.UIClickEvent"}],"__module":"AUIPlugin"},{"texture_name":"hl_align.png","height_type":1,"__link":"_tool_h_align_left_icon","height_value":15,"disabled":true,"width_type":1,"__class":"Image","width_value":13,"y_type":3,"x_value":149.75},{"x_value":99,"__link":"_tool_scale","height_value":25,"__extends":"usual_status_button","group_name":"idetoolbutton201602011338","y_type":3,"width_value":30,"__event":[{"func":"HandleToolScale","type":"ALittle.UIChangedEvent"}],"__module":"AUIPlugin"},{"__class":"Image","x_value":107,"y_type":3,"height_value":17,"disabled":true,"width_value":16,"texture_name":"tool_scale.png"},{"__link":"_tool_h_align_center","x_value":170,"y_type":3,"height_value":25,"__extends":"tool_button","width_value":25,"__event":[{"func":"HandleToolHLAlign","type":"ALittle.UIClickEvent"}],"__module":"AUIPlugin"},{"texture_name":"hc_align.png","height_type":1,"__link":"_tool_h_align_center_icon","height_value":17,"disabled":true,"width_type":1,"__class":"Image","width_value":11,"y_type":3,"x_value":177},{"__link":"_tool_h_align_right","x_value":196,"y_type":3,"height_value":25,"__extends":"tool_button","width_value":25,"__event":[{"func":"HandleToolHLAlign","type":"ALittle.UIClickEvent"}],"__module":"AUIPlugin"},{"texture_name":"hr_align.png","height_type":1,"__link":"_tool_h_align_right_icon","height_value":15,"disabled":true,"width_type":1,"__class":"Image","width_value":13,"y_type":3,"x_value":202},{"__link":"_tool_v_align_top","x_value":224,"y_type":3,"height_value":25,"__extends":"tool_button","width_value":25,"__event":[{"func":"HandleToolHLAlign","type":"ALittle.UIClickEvent"}],"__module":"AUIPlugin"},{"__class":"Image","x_value":230,"__link":"_tool_v_align_top_icon","height_value":14,"disabled":true,"width_type":1,"texture_name":"vt_align.png","y_type":3,"width_value":14,"y_value":1,"height_type":1},{"__link":"_tool_v_align_center","x_value":252,"y_type":3,"height_value":25,"__extends":"tool_button","width_value":25,"__event":[{"func":"HandleToolHLAlign","type":"ALittle.UIClickEvent"}],"__module":"AUIPlugin"},{"__class":"Image","x_value":257,"__link":"_tool_v_align_center_icon","height_value":12,"disabled":true,"width_type":1,"texture_name":"vc_align.png","y_type":3,"width_value":16,"y_value":1,"height_type":1},{"__link":"_tool_v_align_bottom","x_value":279.25,"y_type":3,"height_value":25,"__extends":"tool_button","width_value":25,"__event":[{"func":"HandleToolHLAlign","type":"ALittle.UIClickEvent"}],"__module":"AUIPlugin"},{"__class":"Image","x_value":284.75,"__link":"_tool_v_align_bottom_icon","height_value":14,"disabled":true,"width_type":1,"texture_name":"vb_align.png","y_type":3,"width_value":14,"y_value":1,"height_type":1},{"y_value":8.5,"x_value":200,"__link":"_tool_scale_input","__event":[{"func":"HandleToolScaleInputFOCUSOUT","type":"ALittle.UIEnterKeyEvent"},{"func":"HandleToolScaleInputFOCUSOUT","type":"ALittle.UIFocusOutEvent"}],"__extends":"image_input","width_value":57,"visible":false,"__module":"AUIPlugin"},{"y_value":11.5,"x_value":150,"text":"缩放比例","__link":"_tool_scale_text","__extends":"usual_label","__event":[{"func":"HandleToolScaleDrag","type":"ALittle.UIButtonDragEvent"},{"func":"HandleToolScaleMoveIn","type":"ALittle.UIMoveInEvent"},{"func":"HandleToolScaleMoveOut","type":"ALittle.UIMoveOutEvent"}],"visible":false,"__module":"AUIPlugin"}],"__link":"_tool_ui_container"},{"__class":"DisplayLayout","height_type":4,"width_type":4,"__childs":[{"y_value":0.5,"x_value":5,"__link":"_tool_jumpprecode","__extends":"usual_button","text":"向前","__event":[{"func":"HandleJumpPreCodeClick","type":"ALittle.UIClickEvent"}],"width_value":36,"y_type":3,"__module":"AUIPlugin"},{"y_value":0.5,"x_value":43,"__link":"_tool_jumpnextcode","__extends":"usual_button","text":"向后","__event":[{"func":"HandleJumpNextCodeClick","type":"ALittle.UIClickEvent"}],"width_value":36,"y_type":3,"__module":"AUIPlugin"},{"y_value":0.5,"x_value":152.5,"__link":"_tool_language","__event":[{"func":"HandleTargetLanguageSelectChange","type":"ALittle.UISelectChangedEvent"}],"text":"Lua","width_value":103,"y_type":3,"data_list":["Lua","JavaScript"],"__extends":"dropdown","__module":"AUIPlugin"},{"y_value":0.5,"x_value":98,"text":"目标语言:","__extends":"usual_label","y_type":3,"__module":"AUIPlugin"}],"__link":"_tool_code_container"},{"__class":"DisplayLayout","height_type":4,"width_type":4,"__childs":[{"x_value":8,"__link":"_tool_tile_brush","height_value":25,"__extends":"usual_status_button","group_name":"idetoolbutton201602011338","y_type":3,"__event":[{"func":"HandleToolTileBrushSelect","type":"ALittle.UIChangedEvent"}],"width_value":30,"selected":true,"__module":"AUIPlugin"},{"texture_name":"brush.png","x_value":15,"y_type":3,"height_value":20,"disabled":true,"width_value":20,"__class":"Image"},{"x_value":38,"__link":"_tool_tile_handdrag","height_value":25,"__extends":"usual_status_button","group_name":"idetoolbutton201602011338","y_type":3,"width_value":30,"__event":[{"func":"HandleToolTileHandDrag","type":"ALittle.UIChangedEvent"}],"__module":"AUIPlugin"},{"texture_name":"tool_hold.png","x_value":44,"y_type":3,"height_value":17,"disabled":true,"width_value":17,"__class":"Image"},{"x_value":69,"__link":"_tool_tile_erase","height_value":25,"__extends":"usual_status_button","group_name":"idetoolbutton201602011338","y_type":3,"width_value":30,"__event":[{"func":"HandleToolTileErase","type":"ALittle.UIChangedEvent"}],"__module":"AUIPlugin"},{"texture_name":"Erase.png","x_value":77,"y_type":3,"height_value":16,"disabled":true,"width_value":16,"__class":"Image"},{"x_value":100,"__link":"_tool_tile_select","height_value":25,"__event":[{"type":"ALittle.UIChangedEvent","func":"HandleToolTileSelect"}],"group_name":"idetoolbutton201602011338","y_type":3,"width_value":30,"__extends":"usual_status_button","__module":"AUIPlugin"},{"__class":"Image","x_value":107,"y_type":3,"height_value":14,"disabled":true,"width_value":17,"texture_name":"tool_move.png"}],"__link":"_tool_tile_container"},{"text":"代码搜索","x_value":67,"y_type":3,"x_type":4,"__extends":"usual_button","width_value":66,"__event":[{"func":"HandleFindFileClick","type":"ALittle.UIClickEvent"}],"__module":"AUIPlugin"},{"x_value":8,"y_type":3,"x_type":4,"__extends":"usual_button","__event":[{"func":"HandleImageSelectClick","type":"ALittle.UIClickEvent"}],"text":"图片库","__module":"AUIPlugin"}]}}],"__link":"_center","__class":"DisplayLayout"},"type":2}]}}